src/block.v
/*
 * In The Name Of God
 * ========================================
 * [] File Name : block.v
 *
 * [] Creation Date : 04-03-2015
 *
 * [] Last Modified : Tue, Mar 31, 2015  7:56:39 PM
 *
 * [] Created By : Parham Alvani (parham.alvani@gmail.com)
 * =======================================
*/
module block(enable, write, rst, data_in, data_out, ack);
	
	input enable;
	input write;
	input rst;
	input [0:15] data_in;

	output reg [0:15] data_out = 16'h0000;
	output reg ack = 1'b0;

	reg [0:15] data = 16'h0000;

	always @ (enable) begin
		ack = 1'b0;
		if (enable) begin
			if (write)
				data = data_in;
			if (rst)
				data = 16'h0000;
			data_out <= data;
			ack <= 1'b1;
		end
	end
endmodule

src/set.v
/*
 * In The Name Of God
 * ========================================
 * [] File Name : set.v
 *
 * [] Creation Date : 04-03-2015
 *
 * [] Last Modified : Tue, Mar 31, 2015 11:00:04 PM
 *
 * [] Created By : Parham Alvani (parham.alvani@gmail.com)
 * =======================================
*/
module set (enable, word, comp,
	write, rst, tag_in, data_in, valid_in,
	hit, dirty_out, tag_out,
	data_out, valid_out, ack);
	
	/* set number of block in a set */
	parameter N = 4;

	input enable;
	input rst;
	input [0:1] word;
	input comp;
	input write;
	input rst;
	input [0:4] tag_in;
	input [0:15] data_in;
	input valid_in;

	output reg hit;
	output reg dirty_out;
	output reg [0:4] tag_out;
	output reg [0:15] data_out;
	output reg valid_out;
	output reg ack;

	reg [0:4] tag;
	reg valid = 1'b0;
	reg dirty = 1'b0;

	reg [0:15] word_in [0:N - 1];
	reg word_en [0:N - 1];
	reg word_wr [0:N - 1];
	wire [0:15] word_out [0:N - 1];
	wire word_ack [0:N - 1];

	generate
	genvar i;
	for (i = 0; i < N; i = i + 1) begin
		block blk_ins(word_en[i], word_wr[i], 1'b0, word_in[i], word_out[i], word_ack[i]);
	end
	endgenerate

	always @ (enable) begin
		ack = 1'b0;
		if (enable) begin
			/* Reset */
			if (rst) begin
				valid = 1'b0;
				ack = 1'b1;
			end
			/* Compare Read */
			if (comp && !write) begin
				if (tag == tag_in) begin
					/* HIT */
					hit = 1'b1;
					valid_out = valid;
					dirty_out = dirty;
					tag_out = tag;
					word_en[word] = 1'b1;

					/* waiting for block ack */
					wait (word_ack[word]) begin
						data_out = word_out[word];
					end

					ack = 1'b1;
				end else begin
					/* MISS */
					hit = 1'b0;
					valid_out = valid;
					dirty_out = dirty;
					ack = 1'b1;
				end
			end
			/* Compare Write */
			if (comp && write)  begin
				if (tag == tag_in && valid) begin
					/* HIT -- Valid */
					dirty = 1'b1;
					dirty_out = 1'b0;
					hit = 1'b1;
					word_en[word] = 1'b1;
					word_wr[word] = 1'b1;
					word_in[word] = data_in;

					/* waiting for block ack */
					wait (word_ack[word]) begin
					end
					
					ack = 1'b1;
				end else begin
					/* MISS -- Valid */
					valid_out = valid;
					dirty_out = dirty;
					ack = 1'b1;
				end
			end
			/* Access Read */
			if (!comp && !write) begin
				dirty_out = dirty;
				valid_out = valid;
				tag_out = tag;

				ack = 1'b1;
			end
			/* Access Write */
			if (!comp && write) begin
				tag <= tag_in;
				valid <= valid_in;
				dirty <= 1'b0;
				word_in[word] <= data_in;
				word_wr[word] <= 1'b1;
				word_en[word] <= 1'b1;

				/* waiting for block ack */
				wait (word_ack[word]) begin
					ack = 1'b1;
				end
			end
		end else begin
			word_en[word] = 1'b0;
			word_wr[word] = 1'b0;
			hit = 1'b0;
		end
	end	
endmodule

src/set_t.v
/*
 * In The Name Of God
 * ========================================
 * [] File Name : set_t.v
 *
 * [] Creation Date : 04-03-2015
 *
 * [] Last Modified : Tue, Mar 31, 2015  9:13:43 AM
 *
 * [] Created By : Parham Alvani (parham.alvani@gmail.com)
 * =======================================
*/
`timescale 1 ns/100 ps

module set_t;
	reg [0:15] data_in;
	reg [0:4] tag;
	reg enable;
	reg write;
	reg [0:1] word;
	reg cmp;
	reg valid_in;
	reg rst;

	wire [0:15] data_out;
	wire [0:4] tag_out;
	wire hit;
	wire dirty;
	wire valid;
	wire ack;

	initial begin
		$dumpfile("set.vcd");
		$dumpvars(0, set_t);
		enable = 0;
		rst = 0;
		word = 2'b11;
		valid_in = 1'b1;
		data_in = 16'b0000_1111_0000_1111;
		tag = 5'b11101;
		#5
		write = 1;
		cmp = 0;
		enable = 1;
		#5
		enable = 0;
		#5
		enable = 1;
		write = 0;
		cmp = 1;
		#5
		enable = 0;
		write = 0;
		cmp = 0;
		#5
		enable = 1;
		rst = 1;
		#5
		enable = 0;
		#5
		enable = 1;
		write = 0;
		cmp = 1;
		#10
		$stop;
	end

	set st(enable, word, cmp, write, rst, tag, data_in,
		valid_in, hit, dirty, tag_out, data_out, valid, ack);
endmodule

src/set.vcd
$date
	Tue Mar 31 20:02:43 2015
$end
$version
	ModelSim Version 10.1c
$end
$timescale
	100ps
$end
$scope module set_t $end
$var reg 16 ! data_in [0:15] $end
$var reg 5 " tag [0:4] $end
$var reg 1 # enable $end
$var reg 1 $ write $end
$var reg 2 % word [0:1] $end
$var reg 1 & cmp $end
$var reg 1 ' valid_in $end
$var reg 1 ( rst $end
$var wire 1 ) data_out [0] $end
$var wire 1 * data_out [1] $end
$var wire 1 + data_out [2] $end
$var wire 1 , data_out [3] $end
$var wire 1 - data_out [4] $end
$var wire 1 . data_out [5] $end
$var wire 1 / data_out [6] $end
$var wire 1 0 data_out [7] $end
$var wire 1 1 data_out [8] $end
$var wire 1 2 data_out [9] $end
$var wire 1 3 data_out [10] $end
$var wire 1 4 data_out [11] $end
$var wire 1 5 data_out [12] $end
$var wire 1 6 data_out [13] $end
$var wire 1 7 data_out [14] $end
$var wire 1 8 data_out [15] $end
$var wire 1 9 tag_out [0] $end
$var wire 1 : tag_out [1] $end
$var wire 1 ; tag_out [2] $end
$var wire 1 < tag_out [3] $end
$var wire 1 = tag_out [4] $end
$var wire 1 > hit $end
$var wire 1 ? dirty $end
$var wire 1 @ valid $end
$var wire 1 A ack $end
$scope module st $end
$var parameter 32 B N $end
$var wire 1 C enable $end
$var wire 1 D rst $end
$var wire 1 E word [0] $end
$var wire 1 F word [1] $end
$var wire 1 G comp $end
$var wire 1 H write $end
$var wire 1 I tag_in [0] $end
$var wire 1 J tag_in [1] $end
$var wire 1 K tag_in [2] $end
$var wire 1 L tag_in [3] $end
$var wire 1 M tag_in [4] $end
$var wire 1 N data_in [0] $end
$var wire 1 O data_in [1] $end
$var wire 1 P data_in [2] $end
$var wire 1 Q data_in [3] $end
$var wire 1 R data_in [4] $end
$var wire 1 S data_in [5] $end
$var wire 1 T data_in [6] $end
$var wire 1 U data_in [7] $end
$var wire 1 V data_in [8] $end
$var wire 1 W data_in [9] $end
$var wire 1 X data_in [10] $end
$var wire 1 Y data_in [11] $end
$var wire 1 Z data_in [12] $end
$var wire 1 [ data_in [13] $end
$var wire 1 \ data_in [14] $end
$var wire 1 ] data_in [15] $end
$var wire 1 ^ valid_in $end
$var reg 1 _ hit $end
$var reg 1 ` dirty_out $end
$var reg 5 a tag_out [0:4] $end
$var reg 16 b data_out [0:15] $end
$var reg 1 c valid_out $end
$var reg 1 d ack $end
$var reg 5 e tag [0:4] $end
$var reg 1 f valid $end
$var reg 1 g dirty $end
$var wire 1 h word_out $end
$var wire 1 i word_ack $end
$scope begin genblk1[3] $end
$var parameter 32 j i $end
$scope module blk_ins $end
$var wire 1 k enable $end
$var wire 1 l write $end
$var wire 1 m rst $end
$var wire 1 n data_in [0] $end
$var wire 1 o data_in [1] $end
$var wire 1 p data_in [2] $end
$var wire 1 q data_in [3] $end
$var wire 1 r data_in [4] $end
$var wire 1 s data_in [5] $end
$var wire 1 t data_in [6] $end
$var wire 1 u data_in [7] $end
$var wire 1 v data_in [8] $end
$var wire 1 w data_in [9] $end
$var wire 1 x data_in [10] $end
$var wire 1 y data_in [11] $end
$var wire 1 z data_in [12] $end
$var wire 1 { data_in [13] $end
$var wire 1 | data_in [14] $end
$var wire 1 } data_in [15] $end
$var reg 16 ~ data_out [0:15] $end
$var reg 1 !! ack $end
$var reg 16 "! data [0:15] $end
$upscope $end
$upscope $end
$scope begin genblk1[2] $end
$var parameter 32 #! i $end
$scope module blk_ins $end
$var wire 1 $! enable $end
$var wire 1 %! write $end
$var wire 1 &! rst $end
$var wire 1 '! data_in [0] $end
$var wire 1 (! data_in [1] $end
$var wire 1 )! data_in [2] $end
$var wire 1 *! data_in [3] $end
$var wire 1 +! data_in [4] $end
$var wire 1 ,! data_in [5] $end
$var wire 1 -! data_in [6] $end
$var wire 1 .! data_in [7] $end
$var wire 1 /! data_in [8] $end
$var wire 1 0! data_in [9] $end
$var wire 1 1! data_in [10] $end
$var wire 1 2! data_in [11] $end
$var wire 1 3! data_in [12] $end
$var wire 1 4! data_in [13] $end
$var wire 1 5! data_in [14] $end
$var wire 1 6! data_in [15] $end
$var reg 16 7! data_out [0:15] $end
$var reg 1 8! ack $end
$var reg 16 9! data [0:15] $end
$upscope $end
$upscope $end
$scope begin genblk1[1] $end
$var parameter 32 :! i $end
$scope module blk_ins $end
$var wire 1 ;! enable $end
$var wire 1 <! write $end
$var wire 1 =! rst $end
$var wire 1 >! data_in [0] $end
$var wire 1 ?! data_in [1] $end
$var wire 1 @! data_in [2] $end
$var wire 1 A! data_in [3] $end
$var wire 1 B! data_in [4] $end
$var wire 1 C! data_in [5] $end
$var wire 1 D! data_in [6] $end
$var wire 1 E! data_in [7] $end
$var wire 1 F! data_in [8] $end
$var wire 1 G! data_in [9] $end
$var wire 1 H! data_in [10] $end
$var wire 1 I! data_in [11] $end
$var wire 1 J! data_in [12] $end
$var wire 1 K! data_in [13] $end
$var wire 1 L! data_in [14] $end
$var wire 1 M! data_in [15] $end
$var reg 16 N! data_out [0:15] $end
$var reg 1 O! ack $end
$var reg 16 P! data [0:15] $end
$upscope $end
$upscope $end
$scope begin genblk1[0] $end
$var parameter 32 Q! i $end
$scope module blk_ins $end
$var wire 1 R! enable $end
$var wire 1 S! write $end
$var wire 1 T! rst $end
$var wire 1 U! data_in [0] $end
$var wire 1 V! data_in [1] $end
$var wire 1 W! data_in [2] $end
$var wire 1 X! data_in [3] $end
$var wire 1 Y! data_in [4] $end
$var wire 1 Z! data_in [5] $end
$var wire 1 [! data_in [6] $end
$var wire 1 \! data_in [7] $end
$var wire 1 ]! data_in [8] $end
$var wire 1 ^! data_in [9] $end
$var wire 1 _! data_in [10] $end
$var wire 1 `! data_in [11] $end
$var wire 1 a! data_in [12] $end
$var wire 1 b! data_in [13] $end
$var wire 1 c! data_in [14] $end
$var wire 1 d! data_in [15] $end
$var reg 16 e! data_out [0:15] $end
$var reg 1 f! ack $end
$var reg 16 g! data [0:15] $end
$upscope $end
$upscope $end
$upscope $end
$upscope $end
$enddefinitions $end
#0
$dumpvars
b111100001111 !
b11101 "
0#
x$
b11 %
x&
1'
0(
0_
x`
bx a
bx b
xc
0d
bx e
0f
0g
b0 e!
0f!
b0 g!
b0 N!
0O!
b0 P!
b0 7!
08!
b0 9!
b0 ~
0!!
b0 "!
b100 B
b0 Q!
b1 :!
b10 #!
b11 j
x8
x7
x6
x5
x4
x3
x2
x1
x0
x/
x.
x-
x,
x+
x*
x)
x=
x<
x;
x:
x9
0>
x?
x@
0A
0h
0i
1^
1]
1\
1[
1Z
0Y
0X
0W
0V
1U
1T
1S
1R
0Q
0P
0O
0N
1M
0L
1K
1J
1I
0D
xH
xG
1F
1E
0C
xd!
xc!
xb!
xa!
x`!
x_!
x^!
x]!
x\!
x[!
xZ!
xY!
xX!
xW!
xV!
xU!
0T!
xS!
xR!
xM!
xL!
xK!
xJ!
xI!
xH!
xG!
xF!
xE!
xD!
xC!
xB!
xA!
x@!
x?!
x>!
0=!
x<!
x;!
x6!
x5!
x4!
x3!
x2!
x1!
x0!
x/!
x.!
x-!
x,!
x+!
x*!
x)!
x(!
x'!
0&!
x%!
x$!
x}
x|
x{
xz
xy
xx
xw
xv
xu
xt
xs
xr
xq
xp
xo
xn
0m
0l
0k
$end
#50
1$
0&
1#
1H
0G
1C
b11101 e
1f
1}
1|
1{
1z
0y
0x
0w
0v
1u
1t
1s
1r
0q
0p
0o
0n
1l
1k
b111100001111 "!
b111100001111 ~
1!!
1d
1A
#100
0#
0C
0d
0A
0l
0k
0!!
#150
1#
0$
1&
0H
1G
1C
1_
1c
0`
1>
1@
0?
1k
1!!
b111100001111 b
1d
18
17
16
15
04
03
02
01
10
1/
1.
1-
0,
0+
0*
0)
1A
#200
0#
0&
0G
0C
0d
0_
0A
0>
0k
0!!
#250
1#
1(
1D
1C
0f
1d
0c
b11101 a
1A
0@
1=
0<
1;
1:
19
#300
0#
0C
0d
0A
#350
1#
1&
1G
1C
1d
1_
1A
1>
1k
1!!
