src/fibonacci_lfsr.v
/*
 * In The Name Of God
 * ========================================
 * [] File Name : fibonacci_lfsr.v
 *
 * [] Creation Date : 31-03-2015
 *
 * [] Last Modified : Tue 31 Mar 2015 12:02:42 PM IRDT
 *
 * [] Created By : Parham Alvani (parham.alvani@gmail.com)
 * =======================================
*/

/*
 * based on:
 * http://stackoverflow.com/questions/
 * 14497877/how-to-implement-a-pseudo-hardware-random-number-generator
*/
module fibonacci_lfsr (enable, rst, data);
   	parameter BITS = 5;

	input enable;
    	input rst;
	output reg [BITS - 1:0] data;

	reg [BITS - 1:0] data_next;

	always @* begin
      		data_next = data;
      		repeat(BITS) begin
         		data_next = {(data_next[BITS - 1]^data_next[1]), data_next[BITS - 1:1]};
      		end
   	end

   	always @(enable) begin
		if (enable) begin
      			if (rst) begin
         			data <= 5'h1f;
      			end else begin
         			data <= data_next;
      			end
		end
   	end
endmodule

src/block.v
/*
 * In The Name Of God
 * ========================================
 * [] File Name : block.v
 *
 * [] Creation Date : 04-03-2015
 *
 * [] Last Modified : Tue 31 Mar 2015 08:03:47 AM IRDT
 *
 * [] Created By : Parham Alvani (parham.alvani@gmail.com)
 * =======================================
*/
module block(enable, write, rst, data_in, data_out, ack);
	
	input enable;
	input write;
	input rst;
	input [0:15] data_in;

	output reg [0:15] data_out;
	output reg ack;

	reg [0:15] data;

	always @ (enable, write) begin
		ack = 1'b0;
		if (enable) begin
			if (write)
				data = data_in;
			if (rst)
				data = 16'h0000;
			data_out = data;
			ack = 1'b1;
		end
	end
endmodule

src/set.v
/*
 * In The Name Of God
 * ========================================
 * [] File Name : set.v
 *
 * [] Creation Date : 04-03-2015
 *
 * [] Last Modified : Tue, Mar 31, 2015 11:00:04 PM
 *
 * [] Created By : Parham Alvani (parham.alvani@gmail.com)
 * =======================================
*/
module set (enable, word, comp,
	write, rst, tag_in, data_in, valid_in,
	hit, dirty_out, tag_out,
	data_out, valid_out, ack);
	
	/* set number of block in a set */
	parameter N = 4;

	input enable;
	input rst;
	input [0:1] word;
	input comp;
	input write;
	input rst;
	input [0:4] tag_in;
	input [0:15] data_in;
	input valid_in;

	output reg hit;
	output reg dirty_out;
	output reg [0:4] tag_out;
	output reg [0:15] data_out;
	output reg valid_out;
	output reg ack;

	reg [0:4] tag;
	reg valid = 1'b0;
	reg dirty = 1'b0;

	reg [0:15] word_in [0:N - 1];
	reg word_en [0:N - 1];
	reg word_wr [0:N - 1];
	wire [0:15] word_out [0:N - 1];
	wire word_ack [0:N - 1];

	generate
	genvar i;
	for (i = 0; i < N; i = i + 1) begin
		block blk_ins(word_en[i], word_wr[i], 1'b0, word_in[i], word_out[i], word_ack[i]);
	end
	endgenerate

	always @ (enable) begin
		ack = 1'b0;
		if (enable) begin
			/* Reset */
			if (rst) begin
				valid = 1'b0;
				ack = 1'b1;
			end
			/* Compare Read */
			if (comp && !write) begin
				if (tag == tag_in) begin
					/* HIT */
					hit = 1'b1;
					valid_out = valid;
					dirty_out = dirty;
					tag_out = tag;
					word_en[word] = 1'b1;

					/* waiting for block ack */
					wait (word_ack[word]) begin
						data_out = word_out[word];
					end

					ack = 1'b1;
				end else begin
					/* MISS */
					hit = 1'b0;
					valid_out = valid;
					dirty_out = dirty;
					ack = 1'b1;
				end
			end
			/* Compare Write */
			if (comp && write)  begin
				if (tag == tag_in && valid) begin
					/* HIT -- Valid */
					dirty = 1'b1;
					dirty_out = 1'b0;
					hit = 1'b1;
					word_en[word] = 1'b1;
					word_wr[word] = 1'b1;
					word_in[word] = data_in;

					/* waiting for block ack */
					wait (word_ack[word]) begin
					end
					
					ack = 1'b1;
				end else begin
					/* MISS -- Valid */
					valid_out = valid;
					dirty_out = dirty;
					ack = 1'b1;
				end
			end
			/* Access Read */
			if (!comp && !write) begin
				dirty_out = dirty;
				valid_out = valid;
				tag_out = tag;

				ack = 1'b1;
			end
			/* Access Write */
			if (!comp && write) begin
				tag <= tag_in;
				valid <= valid_in;
				dirty <= 1'b0;
				word_in[word] <= data_in;
				word_wr[word] <= 1'b1;
				word_en[word] <= 1'b1;

				/* waiting for block ack */
				wait (word_ack[word]) begin
					ack = 1'b1;
				end
			end
		end else begin
			word_en[word] = 1'b0;
			word_wr[word] = 1'b0;
			hit = 1'b0;
		end
	end	
endmodule

src/way.v
/*
 * In The Name Of God
 * ========================================
 * [] File Name : way.v
 *
 * [] Creation Date : 31-03-2015
 *
 * [] Last Modified : Tue, Mar 31, 2015 10:58:49 PM
 *
 * [] Created By : Parham Alvani (parham.alvani@gmail.com)
 * =======================================
*/
`timescale 1 ns/100 ps

module way (enable, word, comp,
	write, rst, tag_in, data_in, valid_in,
	hit, dirty_out, tag_out,
	data_out, valid_out, ack);

	parameter N = 2;

	input enable;
	input rst;
	input [0:1] word;
	input comp;
	input write;
	input rst;
	input [0:4] tag_in;
	input [0:15] data_in;
	input valid_in;

	output reg hit;
	output reg dirty_out;
	output reg [0:4] tag_out;
	output reg [0:15] data_out;
	output reg valid_out;
	output reg ack;

	reg [0:N - 1] counter;
	reg flag;

	reg set_en [0:N];
	reg [0:1] set_word [0:N];
	reg set_cmp [0:N];
	reg set_wr [0:N];
	reg [0:4] set_tag_in [0:N];
	reg [0:15] set_in [0:N];
	reg set_valid_in [0:N];
	reg set_rst [0:N];

	wire set_hit [0:N];
	wire set_dirty_out [0:N];
	wire [0:4] set_tag_out [0:N];
	wire [0:15] set_out [0:N];
	wire set_valid_out [0:N];
	wire set_ack [0:N];

	generate
	genvar i;
	for (i = 0; i < N; i = i + 1) begin
		set set_ins (set_en[i], set_word[i], set_cmp[i], set_wr[i], 1'b0,
			set_tag_in[i], set_in[i], set_valid_in[i], set_hit[i], set_dirty_out[i],
			set_tag_out[i], set_out[i], set_valid_out[i], set_ack[i]);
	end
	endgenerate

	reg rand_en;
	reg rand_rst = 1'b0;
	wire [4:0] rand;

	fibonacci_lfsr rnd (rand_en, rand_rst, rand);

	always @ (enable) begin
		ack = 1'b0;
		if (enable) begin
			/* Reset */
			/* Compare Read */
			if (comp && !write) begin
				for (counter = 0; counter < N; counter = counter + 1) begin
					set_tag_in[counter] = tag_in;
					set_wr[counter] = write;
					set_cmp[counter] = comp;
					set_word [counter] = word;
					set_en[counter] = 1'b1;
					
					/* waiting for set ack */
					wait (set_ack[counter]) begin
						if (set_hit[counter]) begin
							/* ONE HIT */
							hit = 1'b1;
							valid_out = set_valid_out[counter];
							dirty_out = set_dirty_out[counter];
							data_out = set_out[counter];
							tag_out = set_tag_out[counter];
							set_en[counter] = 1'b0;
						end else begin
							set_en[counter] = 1'b0;
						end
					end
				end
				if (!hit) begin
					/* ALL MISS */
					hit = 1'b0;
				end
				ack = 1'b1;
			end
			/* Compare Write */
			if (comp && write) begin
				for (counter = 0; counter < N; counter = counter + 1) begin
					set_en[counter] = 1'b1;
					set_tag_in[counter] = tag_in;
					set_in[counter] = data_in;
	
					/* waiting for set ack */
					wait (set_ack[counter]) begin
						if (set_hit[counter]) begin
							/* HIT -- Valid */
							hit = 1'b1;
							set_en[counter] = 1'b0;
						end else begin
							set_en[counter] = 1'b0;
						end
					end
				end
				if (!hit) begin
					/* MISS -- Valid */
					hit = 1'b0;
				end
				ack = 1'b1;
			end
			/* Access Read */
			if (!comp && !write) begin
				ack = 1'b1;
			end
			/* Access Write */
			if (!comp && write) begin
				flag = 0;
				for (counter = 0; counter < N; counter = counter + 1) begin
					set_in[counter] = data_in;
					set_cmp[counter] = 1'b0;
					set_wr[counter] = 1'b0;
					set_en[counter] = 1'b1;

					/* waiting for set ack */
					wait (set_ack[counter]) begin
						if (!set_valid_out[counter] && !flag) begin
							#1
							flag = 1;
							set_en[counter] = 1'b0;
							wait (!set_ack[counter]) begin
							end
							/*
							 * just for better
							 * wave formats
							*/
							#1
							set_word[counter] = word;
							set_valid_in[counter] = valid_in;
							set_tag_in[counter] = tag_in;
							set_wr[counter] = 1'b1;
							set_cmp[counter] = 1'b0;
							set_en[counter] = 1'b1;
							#1
							wait (set_ack[counter]) begin
								set_en[counter] = 1'b0;
							end
						end
					end

				end
				if (!flag) begin
					rand_en = 1'b1;
					
					set_in[rand[4]] = data_in;
					set_word[rand[4]] = word;
					set_valid_in[rand[4]] = valid_in;
					set_tag_in[rand[4]] = tag_in;
					set_wr[rand[4]] = 1'b1;
					set_cmp[rand[4]] = 1'b0;
					set_en[rand[4]] = 1'b1;
					wait (set_ack[rand[4]]) begin
					end
					set_en[rand[4]] = 1'b0;
					rand_en = 1'b0;
				end
				ack = 1'b1;
			end
		end else begin
			hit = 1'b0;
		end
	end
endmodule

src/way_t.v
/*
 * In The Name Of God
 * ========================================
 * [] File Name : way_t.v
 *
 * [] Creation Date : 04-03-2015
 *
 * [] Last Modified : Tue, Mar 31, 2015 10:56:44 PM
 *
 * [] Created By : Parham Alvani (parham.alvani@gmail.com)
 * =======================================
*/
`timescale 1 ns/100 ps

module way_t;
	reg [0:15] data_in = 16'h0f0f;
	reg [0:4] tag;
	reg enable = 1'b0;
	reg write = 1'b0;
	reg [0:1] word;
	reg cmp;
	reg valid_in;
	reg rst;

	wire [0:15] data_out;
	wire [0:4] tag_out;
	wire hit;
	wire dirty;
	wire valid;
	wire ack;

	initial begin
		$dumpfile("way.vcd");
		$dumpvars(0, way_t);
		enable <= 0;
		rst <= 0;
		word <= 2'b11;
		valid_in <= 1'b1;
		data_in <= 16'h0f0f;
		tag <= 5'b11101;
		#5
		enable <= 1;
		write <= 1;
		cmp <= 0;
		#5
		enable <= 0;
		#5
		enable <= 1;
		write <= 0;
		cmp <= 1;
		#5
		enable <= 0;
		write <= 0;
		cmp <= 0;
		#5
		enable <= 1;
		rst <= 1;
		wait (ack) begin
		end
		#5
		rst <= 0;
		enable <= 0;
		#5
		enable <= 1;
		write <= 0;
		cmp <= 1;
		#10
		$stop;
	end

	way wy(enable, word, cmp, write, rst, tag, data_in,
		valid_in, hit, dirty, tag_out, data_out, valid, ack);
endmodule

src/way.vcd
$date
	Tue Mar 31 23:01:16 2015
$end
$version
	ModelSim Version 10.1c
$end
$timescale
	100ps
$end
$scope module way_t $end
$var reg 16 ! data_in [0:15] $end
$var reg 5 " tag [0:4] $end
$var reg 1 # enable $end
$var reg 1 $ write $end
$var reg 2 % word [0:1] $end
$var reg 1 & cmp $end
$var reg 1 ' valid_in $end
$var reg 1 ( rst $end
$var wire 1 ) data_out [0] $end
$var wire 1 * data_out [1] $end
$var wire 1 + data_out [2] $end
$var wire 1 , data_out [3] $end
$var wire 1 - data_out [4] $end
$var wire 1 . data_out [5] $end
$var wire 1 / data_out [6] $end
$var wire 1 0 data_out [7] $end
$var wire 1 1 data_out [8] $end
$var wire 1 2 data_out [9] $end
$var wire 1 3 data_out [10] $end
$var wire 1 4 data_out [11] $end
$var wire 1 5 data_out [12] $end
$var wire 1 6 data_out [13] $end
$var wire 1 7 data_out [14] $end
$var wire 1 8 data_out [15] $end
$var wire 1 9 tag_out [0] $end
$var wire 1 : tag_out [1] $end
$var wire 1 ; tag_out [2] $end
$var wire 1 < tag_out [3] $end
$var wire 1 = tag_out [4] $end
$var wire 1 > hit $end
$var wire 1 ? dirty $end
$var wire 1 @ valid $end
$var wire 1 A ack $end
$scope module wy $end
$var parameter 32 B N $end
$var wire 1 C enable $end
$var wire 1 D rst $end
$var wire 1 E word [0] $end
$var wire 1 F word [1] $end
$var wire 1 G comp $end
$var wire 1 H write $end
$var wire 1 I tag_in [0] $end
$var wire 1 J tag_in [1] $end
$var wire 1 K tag_in [2] $end
$var wire 1 L tag_in [3] $end
$var wire 1 M tag_in [4] $end
$var wire 1 N data_in [0] $end
$var wire 1 O data_in [1] $end
$var wire 1 P data_in [2] $end
$var wire 1 Q data_in [3] $end
$var wire 1 R data_in [4] $end
$var wire 1 S data_in [5] $end
$var wire 1 T data_in [6] $end
$var wire 1 U data_in [7] $end
$var wire 1 V data_in [8] $end
$var wire 1 W data_in [9] $end
$var wire 1 X data_in [10] $end
$var wire 1 Y data_in [11] $end
$var wire 1 Z data_in [12] $end
$var wire 1 [ data_in [13] $end
$var wire 1 \ data_in [14] $end
$var wire 1 ] data_in [15] $end
$var wire 1 ^ valid_in $end
$var reg 1 _ hit $end
$var reg 1 ` dirty_out $end
$var reg 5 a tag_out [0:4] $end
$var reg 16 b data_out [0:15] $end
$var reg 1 c valid_out $end
$var reg 1 d ack $end
$var reg 2 e counter [0:1] $end
$var reg 1 f flag $end
$var wire 1 g set_hit $end
$var wire 1 h set_dirty_out $end
$var wire 1 i set_tag_out $end
$var wire 1 j set_out $end
$var wire 1 k set_valid_out $end
$var wire 1 l set_ack $end
$var reg 1 m rand_en $end
$var reg 1 n rand_rst $end
$var wire 1 o rand [4] $end
$var wire 1 p rand [3] $end
$var wire 1 q rand [2] $end
$var wire 1 r rand [1] $end
$var wire 1 s rand [0] $end
$scope begin genblk1[1] $end
$var parameter 32 t i $end
$scope module set_ins $end
$var parameter 32 u N $end
$var wire 1 v enable $end
$var wire 1 w rst $end
$var wire 1 x word [0] $end
$var wire 1 y word [1] $end
$var wire 1 z comp $end
$var wire 1 { write $end
$var wire 1 | tag_in [0] $end
$var wire 1 } tag_in [1] $end
$var wire 1 ~ tag_in [2] $end
$var wire 1 !! tag_in [3] $end
$var wire 1 "! tag_in [4] $end
$var wire 1 #! data_in [0] $end
$var wire 1 $! data_in [1] $end
$var wire 1 %! data_in [2] $end
$var wire 1 &! data_in [3] $end
$var wire 1 '! data_in [4] $end
$var wire 1 (! data_in [5] $end
$var wire 1 )! data_in [6] $end
$var wire 1 *! data_in [7] $end
$var wire 1 +! data_in [8] $end
$var wire 1 ,! data_in [9] $end
$var wire 1 -! data_in [10] $end
$var wire 1 .! data_in [11] $end
$var wire 1 /! data_in [12] $end
$var wire 1 0! data_in [13] $end
$var wire 1 1! data_in [14] $end
$var wire 1 2! data_in [15] $end
$var wire 1 3! valid_in $end
$var reg 1 4! hit $end
$var reg 1 5! dirty_out $end
$var reg 5 6! tag_out [0:4] $end
$var reg 16 7! data_out [0:15] $end
$var reg 1 8! valid_out $end
$var reg 1 9! ack $end
$var reg 5 :! tag [0:4] $end
$var reg 1 ;! valid $end
$var reg 1 <! dirty $end
$var wire 1 =! word_out $end
$var wire 1 >! word_ack $end
$scope begin genblk1[3] $end
$var parameter 32 ?! i $end
$scope module blk_ins $end
$var wire 1 @! enable $end
$var wire 1 A! write $end
$var wire 1 B! rst $end
$var wire 1 C! data_in [0] $end
$var wire 1 D! data_in [1] $end
$var wire 1 E! data_in [2] $end
$var wire 1 F! data_in [3] $end
$var wire 1 G! data_in [4] $end
$var wire 1 H! data_in [5] $end
$var wire 1 I! data_in [6] $end
$var wire 1 J! data_in [7] $end
$var wire 1 K! data_in [8] $end
$var wire 1 L! data_in [9] $end
$var wire 1 M! data_in [10] $end
$var wire 1 N! data_in [11] $end
$var wire 1 O! data_in [12] $end
$var wire 1 P! data_in [13] $end
$var wire 1 Q! data_in [14] $end
$var wire 1 R! data_in [15] $end
$var reg 16 S! data_out [0:15] $end
$var reg 1 T! ack $end
$var reg 16 U! data [0:15] $end
$upscope $end
$upscope $end
$scope begin genblk1[2] $end
$var parameter 32 V! i $end
$scope module blk_ins $end
$var wire 1 W! enable $end
$var wire 1 X! write $end
$var wire 1 Y! rst $end
$var wire 1 Z! data_in [0] $end
$var wire 1 [! data_in [1] $end
$var wire 1 \! data_in [2] $end
$var wire 1 ]! data_in [3] $end
$var wire 1 ^! data_in [4] $end
$var wire 1 _! data_in [5] $end
$var wire 1 `! data_in [6] $end
$var wire 1 a! data_in [7] $end
$var wire 1 b! data_in [8] $end
$var wire 1 c! data_in [9] $end
$var wire 1 d! data_in [10] $end
$var wire 1 e! data_in [11] $end
$var wire 1 f! data_in [12] $end
$var wire 1 g! data_in [13] $end
$var wire 1 h! data_in [14] $end
$var wire 1 i! data_in [15] $end
$var reg 16 j! data_out [0:15] $end
$var reg 1 k! ack $end
$var reg 16 l! data [0:15] $end
$upscope $end
$upscope $end
$scope begin genblk1[1] $end
$var parameter 32 m! i $end
$scope module blk_ins $end
$var wire 1 n! enable $end
$var wire 1 o! write $end
$var wire 1 p! rst $end
$var wire 1 q! data_in [0] $end
$var wire 1 r! data_in [1] $end
$var wire 1 s! data_in [2] $end
$var wire 1 t! data_in [3] $end
$var wire 1 u! data_in [4] $end
$var wire 1 v! data_in [5] $end
$var wire 1 w! data_in [6] $end
$var wire 1 x! data_in [7] $end
$var wire 1 y! data_in [8] $end
$var wire 1 z! data_in [9] $end
$var wire 1 {! data_in [10] $end
$var wire 1 |! data_in [11] $end
$var wire 1 }! data_in [12] $end
$var wire 1 ~! data_in [13] $end
$var wire 1 !" data_in [14] $end
$var wire 1 "" data_in [15] $end
$var reg 16 #" data_out [0:15] $end
$var reg 1 $" ack $end
$var reg 16 %" data [0:15] $end
$upscope $end
$upscope $end
$scope begin genblk1[0] $end
$var parameter 32 &" i $end
$scope module blk_ins $end
$var wire 1 '" enable $end
$var wire 1 (" write $end
$var wire 1 )" rst $end
$var wire 1 *" data_in [0] $end
$var wire 1 +" data_in [1] $end
$var wire 1 ," data_in [2] $end
$var wire 1 -" data_in [3] $end
$var wire 1 ." data_in [4] $end
$var wire 1 /" data_in [5] $end
$var wire 1 0" data_in [6] $end
$var wire 1 1" data_in [7] $end
$var wire 1 2" data_in [8] $end
$var wire 1 3" data_in [9] $end
$var wire 1 4" data_in [10] $end
$var wire 1 5" data_in [11] $end
$var wire 1 6" data_in [12] $end
$var wire 1 7" data_in [13] $end
$var wire 1 8" data_in [14] $end
$var wire 1 9" data_in [15] $end
$var reg 16 :" data_out [0:15] $end
$var reg 1 ;" ack $end
$var reg 16 <" data [0:15] $end
$upscope $end
$upscope $end
$upscope $end
$upscope $end
$scope begin genblk1[0] $end
$var parameter 32 =" i $end
$scope module set_ins $end
$var parameter 32 >" N $end
$var wire 1 ?" enable $end
$var wire 1 @" rst $end
$var wire 1 A" word [0] $end
$var wire 1 B" word [1] $end
$var wire 1 C" comp $end
$var wire 1 D" write $end
$var wire 1 E" tag_in [0] $end
$var wire 1 F" tag_in [1] $end
$var wire 1 G" tag_in [2] $end
$var wire 1 H" tag_in [3] $end
$var wire 1 I" tag_in [4] $end
$var wire 1 J" data_in [0] $end
$var wire 1 K" data_in [1] $end
$var wire 1 L" data_in [2] $end
$var wire 1 M" data_in [3] $end
$var wire 1 N" data_in [4] $end
$var wire 1 O" data_in [5] $end
$var wire 1 P" data_in [6] $end
$var wire 1 Q" data_in [7] $end
$var wire 1 R" data_in [8] $end
$var wire 1 S" data_in [9] $end
$var wire 1 T" data_in [10] $end
$var wire 1 U" data_in [11] $end
$var wire 1 V" data_in [12] $end
$var wire 1 W" data_in [13] $end
$var wire 1 X" data_in [14] $end
$var wire 1 Y" data_in [15] $end
$var wire 1 Z" valid_in $end
$var reg 1 [" hit $end
$var reg 1 \" dirty_out $end
$var reg 5 ]" tag_out [0:4] $end
$var reg 16 ^" data_out [0:15] $end
$var reg 1 _" valid_out $end
$var reg 1 `" ack $end
$var reg 5 a" tag [0:4] $end
$var reg 1 b" valid $end
$var reg 1 c" dirty $end
$var wire 1 d" word_out $end
$var wire 1 e" word_ack $end
$scope begin genblk1[3] $end
$var parameter 32 f" i $end
$scope module blk_ins $end
$var wire 1 g" enable $end
$var wire 1 h" write $end
$var wire 1 i" rst $end
$var wire 1 j" data_in [0] $end
$var wire 1 k" data_in [1] $end
$var wire 1 l" data_in [2] $end
$var wire 1 m" data_in [3] $end
$var wire 1 n" data_in [4] $end
$var wire 1 o" data_in [5] $end
$var wire 1 p" data_in [6] $end
$var wire 1 q" data_in [7] $end
$var wire 1 r" data_in [8] $end
$var wire 1 s" data_in [9] $end
$var wire 1 t" data_in [10] $end
$var wire 1 u" data_in [11] $end
$var wire 1 v" data_in [12] $end
$var wire 1 w" data_in [13] $end
$var wire 1 x" data_in [14] $end
$var wire 1 y" data_in [15] $end
$var reg 16 z" data_out [0:15] $end
$var reg 1 {" ack $end
$var reg 16 |" data [0:15] $end
$upscope $end
$upscope $end
$scope begin genblk1[2] $end
$var parameter 32 }" i $end
$scope module blk_ins $end
$var wire 1 ~" enable $end
$var wire 1 !# write $end
$var wire 1 "# rst $end
$var wire 1 ## data_in [0] $end
$var wire 1 $# data_in [1] $end
$var wire 1 %# data_in [2] $end
$var wire 1 &# data_in [3] $end
$var wire 1 '# data_in [4] $end
$var wire 1 (# data_in [5] $end
$var wire 1 )# data_in [6] $end
$var wire 1 *# data_in [7] $end
$var wire 1 +# data_in [8] $end
$var wire 1 ,# data_in [9] $end
$var wire 1 -# data_in [10] $end
$var wire 1 .# data_in [11] $end
$var wire 1 /# data_in [12] $end
$var wire 1 0# data_in [13] $end
$var wire 1 1# data_in [14] $end
$var wire 1 2# data_in [15] $end
$var reg 16 3# data_out [0:15] $end
$var reg 1 4# ack $end
$var reg 16 5# data [0:15] $end
$upscope $end
$upscope $end
$scope begin genblk1[1] $end
$var parameter 32 6# i $end
$scope module blk_ins $end
$var wire 1 7# enable $end
$var wire 1 8# write $end
$var wire 1 9# rst $end
$var wire 1 :# data_in [0] $end
$var wire 1 ;# data_in [1] $end
$var wire 1 <# data_in [2] $end
$var wire 1 =# data_in [3] $end
$var wire 1 ># data_in [4] $end
$var wire 1 ?# data_in [5] $end
$var wire 1 @# data_in [6] $end
$var wire 1 A# data_in [7] $end
$var wire 1 B# data_in [8] $end
$var wire 1 C# data_in [9] $end
$var wire 1 D# data_in [10] $end
$var wire 1 E# data_in [11] $end
$var wire 1 F# data_in [12] $end
$var wire 1 G# data_in [13] $end
$var wire 1 H# data_in [14] $end
$var wire 1 I# data_in [15] $end
$var reg 16 J# data_out [0:15] $end
$var reg 1 K# ack $end
$var reg 16 L# data [0:15] $end
$upscope $end
$upscope $end
$scope begin genblk1[0] $end
$var parameter 32 M# i $end
$scope module blk_ins $end
$var wire 1 N# enable $end
$var wire 1 O# write $end
$var wire 1 P# rst $end
$var wire 1 Q# data_in [0] $end
$var wire 1 R# data_in [1] $end
$var wire 1 S# data_in [2] $end
$var wire 1 T# data_in [3] $end
$var wire 1 U# data_in [4] $end
$var wire 1 V# data_in [5] $end
$var wire 1 W# data_in [6] $end
$var wire 1 X# data_in [7] $end
$var wire 1 Y# data_in [8] $end
$var wire 1 Z# data_in [9] $end
$var wire 1 [# data_in [10] $end
$var wire 1 \# data_in [11] $end
$var wire 1 ]# data_in [12] $end
$var wire 1 ^# data_in [13] $end
$var wire 1 _# data_in [14] $end
$var wire 1 `# data_in [15] $end
$var reg 16 a# data_out [0:15] $end
$var reg 1 b# ack $end
$var reg 16 c# data [0:15] $end
$upscope $end
$upscope $end
$upscope $end
$upscope $end
$scope module rnd $end
$var parameter 32 d# BITS $end
$var wire 1 e# enable $end
$var wire 1 f# rst $end
$var reg 5 g# data [4:0] $end
$var reg 5 h# data_next [4:0] $end
$upscope $end
$upscope $end
$upscope $end
$enddefinitions $end
#0
$dumpvars
b111100001111 !
b11101 "
0#
0$
b11 %
x&
1'
0(
0_
x`
bx a
bx b
xc
0d
bx e
xf
x["
x\"
bx ]"
bx ^"
x_"
x`"
bx a"
0b"
0c"
b0 a#
0b#
b0 c#
b0 J#
0K#
b0 L#
b0 3#
04#
b0 5#
b0 z"
0{"
b0 |"
x4!
x5!
bx 6!
bx 7!
x8!
x9!
bx :!
0;!
0<!
b0 :"
0;"
b0 <"
b0 #"
0$"
b0 %"
b0 j!
0k!
b0 l!
b0 S!
0T!
b0 U!
xm
0n
b11111 g#
bx h#
b10 B
b101 d#
b0 ="
b100 >"
b1 t
b100 u
b0 M#
b1 6#
b10 }"
b11 f"
b0 &"
b1 m!
b10 V!
b11 ?!
x8
x7
x6
x5
x4
x3
x2
x1
x0
x/
x.
x-
x,
x+
x*
x)
x=
x<
x;
x:
x9
0>
x?
x@
0A
xg
xh
xi
xj
xk
xl
0d"
0e"
0=!
0>!
1s
1r
1q
1p
1o
1^
1]
1\
1[
1Z
0Y
0X
0W
0V
1U
1T
1S
1R
0Q
0P
0O
0N
1M
0L
1K
1J
1I
0D
0H
xG
1F
1E
0C
0f#
xe#
xZ"
xY"
xX"
xW"
xV"
xU"
xT"
xS"
xR"
xQ"
xP"
xO"
xN"
xM"
xL"
xK"
xJ"
xI"
xH"
xG"
xF"
xE"
0@"
xD"
xC"
xB"
xA"
x?"
x3!
x2!
x1!
x0!
x/!
x.!
x-!
x,!
x+!
x*!
x)!
x(!
x'!
x&!
x%!
x$!
x#!
x"!
x!!
x~
x}
x|
0w
x{
xz
xy
xx
xv
x`#
x_#
x^#
x]#
x\#
x[#
xZ#
xY#
xX#
xW#
xV#
xU#
xT#
xS#
xR#
xQ#
0P#
xO#
xN#
xI#
xH#
xG#
xF#
xE#
xD#
xC#
xB#
xA#
x@#
x?#
x>#
x=#
x<#
x;#
x:#
09#
x8#
x7#
x2#
x1#
x0#
x/#
x.#
x-#
x,#
x+#
x*#
x)#
x(#
x'#
x&#
x%#
x$#
x##
0"#
x!#
x~"
xy"
xx"
xw"
xv"
xu"
xt"
xs"
xr"
xq"
xp"
xo"
xn"
xm"
xl"
xk"
xj"
0i"
xh"
xg"
x9"
x8"
x7"
x6"
x5"
x4"
x3"
x2"
x1"
x0"
x/"
x."
x-"
x,"
x+"
x*"
0)"
x("
x'"
x""
x!"
x~!
x}!
x|!
x{!
xz!
xy!
xx!
xw!
xv!
xu!
xt!
xs!
xr!
xq!
0p!
xo!
xn!
xi!
xh!
xg!
xf!
xe!
xd!
xc!
xb!
xa!
x`!
x_!
x^!
x]!
x\!
x[!
xZ!
0Y!
xX!
xW!
xR!
xQ!
xP!
xO!
xN!
xM!
xL!
xK!
xJ!
xI!
xH!
xG!
xF!
xE!
xD!
xC!
0B!
xA!
x@!
$end
#50
1#
1$
0&
1H
0G
1C
0f
b0 e
1Y"
1X"
1W"
1V"
0U"
0T"
0S"
0R"
1Q"
1P"
1O"
1N"
0M"
0L"
0K"
0J"
0C"
0D"
1?"
0`"
0\"
0_"
1`"
1l
0h
0k
#60
1f
0?"
0`"
0["
0l
0g
#70
1Z"
1I"
0H"
1G"
1F"
1E"
1B"
1A"
1D"
1?"
b11101 a"
1b"
1y"
1x"
1w"
1v"
0u"
0t"
0s"
0r"
1q"
1p"
1o"
1n"
0m"
0l"
0k"
0j"
1h"
1g"
b111100001111 |"
b111100001111 z"
1{"
1`"
1l
#80
b1 e
12!
11!
10!
1/!
0.!
0-!
0,!
0+!
1*!
1)!
1(!
1'!
0&!
0%!
0$!
0#!
0z
0{
1v
0?"
09!
05!
08!
19!
0`"
0l
0h"
0g"
0{"
b10 e
1d
1A
#100
0#
0C
0d
0A
#150
1#
0$
1&
0H
1G
1C
b0 e
0D"
1C"
1?"
1["
1_"
b11101 ]"
1g
1k
1i
1g"
1{"
b111100001111 ^"
1`"
1j
1l
1_
1c
0`
b111100001111 b
b11101 a
b1 e
b10 e
1d
1>
1@
0?
1z
1y
1x
1"!
0!!
1~
1}
1|
1=
0<
1;
1:
19
18
17
16
15
04
03
02
01
10
1/
1.
1-
0,
0+
0*
0)
1A
0v
0?"
09!
04!
0`"
0["
0A!
0l
0g
0@!
0g"
0{"
#200
0#
0&
0G
0C
0d
0_
0A
0>
#250
1#
1(
1D
1C
1d
1A
#300
0(
0#
0D
0C
0d
0A
#350
1#
1&
1G
1C
b0 e
1?"
1["
1g
1g"
1{"
1`"
1l
1_
b1 e
1>
1v
0?"
19!
0`"
0["
0l
0g
0g"
0{"
b10 e
1d
1A
0v
09!
